core/__init__.py
core/basic_models/__init__.py
core/basic_models/actions/__init__.py
core/basic_models/actions/basic_actions.py
core/basic_models/actions/client_profile_actions.py
core/basic_models/actions/command.py
core/basic_models/actions/counter_actions.py
core/basic_models/actions/external_actions.py
core/basic_models/actions/push_action.py
core/basic_models/actions/smartpay.py
core/basic_models/actions/string_actions.py
core/basic_models/actions/variable_actions.py
core/basic_models/answer_items/__init__.py
core/basic_models/answer_items/answer_items.py
core/basic_models/classifiers/__init__.py
core/basic_models/classifiers/basic_classifiers.py
core/basic_models/classifiers/classifiers_constants.py
core/basic_models/classifiers/external_classifiers.py
core/basic_models/classifiers/vectorizer_models.py
core/basic_models/counter/__init__.py
core/basic_models/counter/counter.py
core/basic_models/counter/counters.py
core/basic_models/operators/__init__.py
core/basic_models/operators/comparators.py
core/basic_models/operators/operators.py
core/basic_models/parametrizers/__init__.py
core/basic_models/parametrizers/filter.py
core/basic_models/parametrizers/parametrizer.py
core/basic_models/requirement/__init__.py
core/basic_models/requirement/basic_requirements.py
core/basic_models/requirement/counter_requirements.py
core/basic_models/requirement/device_requirements.py
core/basic_models/requirement/external_requirements.py
core/basic_models/requirement/project_requirements.py
core/basic_models/requirement/user_text_requirements.py
core/basic_models/scenarios/__init__.py
core/basic_models/scenarios/base_scenario.py
core/basic_models/variables/__init__.py
core/basic_models/variables/mid_variables.py
core/basic_models/variables/variables.py
core/configs/__init__.py
core/configs/base_config.py
core/configs/config_constants.py
core/configs/global_constants.py
core/db_adapter/__init__.py
core/db_adapter/aioredis_adapter.py
core/db_adapter/aioredis_sentinel_adapter.py
smart_app_framework-2.3.0.dist-info/METADATA
smart_app_framework-2.3.0.dist-info/WHEEL
smart_app_framework-2.3.0.dist-info/RECORD
