Metadata-Version: 2.3
Name: smart-app-framework
Version: 2.3.0
Summary: Python-фреймворк, который позволяет создавать смартапы для виртуальных ассистентов Салют.
Author: Salute Developers
Author-email: developer@sberdevices.ru
Requires-Python: >=3.8.1,<3.12
Classifier: Operating System :: MacOS
Classifier: Operating System :: POSIX :: Linux
Classifier: Programming Language :: Python :: 3
Classifier: Programming Language :: Python :: 3.9
Classifier: Programming Language :: Python :: 3.10
Classifier: Programming Language :: Python :: 3.11
Provides-Extra: ml
Requires-Dist: Jinja2 (==3.0.3)
Requires-Dist: PyYAML (==6.0.1)
Requires-Dist: TatSu (==5.8.3)
Requires-Dist: aiohttp (==3.10.5)
Requires-Dist: aiokafka (==0.8.1)
Requires-Dist: boto (==2.49.0)
Requires-Dist: cachetools (==5.3.0)
Requires-Dist: certifi (==2023.07.22)
Requires-Dist: croniter (==1.3.7)
Requires-Dist: dill (==0.3.6)
Requires-Dist: freezegun (==1.1.0)
Requires-Dist: ics (==0.6)
Requires-Dist: keras (==2.12.0) ; extra == "ml"
Requires-Dist: lazy (==1.5)
Requires-Dist: lxml (==4.9.2)
Requires-Dist: nltk (==3.9.1)
Requires-Dist: numpy (==1.23.5)
Requires-Dist: objgraph (==3.4.1)
Requires-Dist: prometheus-client (==0.11.0)
Requires-Dist: protobuf (==3.20.3)
Requires-Dist: psutil (==5.9.4)
Requires-Dist: pyignite (==0.5.2)
Requires-Dist: pymorphy2 (==0.8)
Requires-Dist: pymorphy2_dicts (==2.4.393442.3710985)
Requires-Dist: python-dateutil (==2.7.3)
Requires-Dist: python-decouple (==3.4)
Requires-Dist: python-json-logger (==0.1.11)
Requires-Dist: requests (==2.31.0)
Requires-Dist: rusenttokenize (==0.0.5)
Requires-Dist: scikit-learn (==1.1.2) ; (python_version < "3.11") and (extra == "ml")
Requires-Dist: scikit-learn (==1.2.0) ; (python_version >= "3.11.dev0" and python_version < "3.12.dev0") and (extra == "ml")
Requires-Dist: setuptools (==75.2.0)
Requires-Dist: tabulate (==0.9.0)
Requires-Dist: tensorflow (==2.12.0) ; (sys_platform == "darwin" and platform_machine == "x86_64") and (extra == "ml")
Requires-Dist: tensorflow (==2.12.0) ; (sys_platform == "linux" and platform_machine == "x86_64") and (extra == "ml")
Requires-Dist: tensorflow-aarch64 (==2.12.0) ; (sys_platform == "linux" and platform_machine == "aarch64") and (extra == "ml")
Requires-Dist: tensorflow-macos (==2.12.0) ; (sys_platform == "darwin" and platform_machine == "arm64") and (extra == "ml")
Requires-Dist: timeout-decorator (==0.4.1)
Requires-Dist: tqdm (==4.64.1)
Requires-Dist: twisted (==24.11.0)
Requires-Dist: urllib3 (==1.26.18)
